pyupgradex/__init__.py
pyupgradex/__main__.py
pyupgradex-0.0.1.dist-info/LICENSE
pyupgradex-0.0.1.dist-info/METADATA
pyupgradex-0.0.1.dist-info/WHEEL
pyupgradex-0.0.1.dist-info/entry_points.txt
pyupgradex-0.0.1.dist-info/RECORD
