Metadata-Version: 2.1
Name: pyupgradex
Version: 0.0.1
Summary: This is a tool that provides advanced features of pyupgrade.
Home-page: https://github.com/mrlyc/pyupgradex
Author: MrLYC
Author-email: github@m.mrlyc.com
Requires-Python: >=3.8,<4.0
Classifier: Programming Language :: Python :: 3
Classifier: Programming Language :: Python :: 3.8
Classifier: Programming Language :: Python :: 3.9
Classifier: Programming Language :: Python :: 3.10
Classifier: Programming Language :: Python :: 3.11
Classifier: Programming Language :: Python :: 3.12
Classifier: Programming Language :: Python :: 3.13
Requires-Dist: pyupgrade (>=3)
Project-URL: Documentation, https://mrlyc.github.io/pyupgradex/
Project-URL: Repository, https://github.com/mrlyc/pyupgradex
